{
  "acceptance": {
    "all_baked_pages_queried": true,
    "bounded_memory_queues_frames": true,
    "clean_project_boundary": true,
    "clean_shutdown": true,
    "compaction_reopen": true,
    "durable_edit_query_ordering": true,
    "migration_reopen": true,
    "official_mit_backend": true,
    "real_render_collision_transitions": true,
    "required_notices": true
  },
  "case_count": 4,
  "cases": [
    {
      "configuration": "template_debug",
      "distribution": {
        "bytes": 3963075,
        "file_count": 143,
        "sha256": "70864e37045b707b790b647fea187c74ec717b80d5b04df8f5bf5e2c6de3ce71"
      },
      "engine_sha256": "ef90e929ba1a6a4322860285d97f40f4aa349c90329a91b0e8b55b8df0f4cb00",
      "engine_version": "4.6.3",
      "runtime": {
        "actual_duration_ms": 15347,
        "compacted_runtime": {
          "active_chunk_records": 9,
          "application_applied_collision": 9,
          "application_applied_render": 9,
          "application_queue_rejections": 0,
          "application_sink_failures": 0,
          "application_stale_collision": 0,
          "application_stale_render": 0,
          "application_submitted_collision": 9,
          "application_submitted_render": 9,
          "application_unrequired_collision": 0,
          "coalesced_viewer_events": 0,
          "collision_latency_frames_maximum": 1,
          "collision_resources": 5,
          "edit_commits": 0,
          "edit_rejections": 0,
          "edit_replacements": 0,
          "fully_ready_chunk_records": 9,
          "mesh_completions": 9,
          "mesh_jobs": 9,
          "pending_chunk_retirements": 0,
          "planned_demands": 9,
          "published_events": 29,
          "queued_collision": 0,
          "queued_render": 0,
          "rejected_events": 0,
          "render_fading_resources": 0,
          "render_latency_frames_maximum": 1,
          "render_resources": 5,
          "sample_jobs": 9,
          "sample_queries": 1,
          "sample_query_rejections": 0,
          "storage_completions": 13,
          "transition_mesh_completions": 1,
          "viewer_removals": 0,
          "viewer_updates": 1,
          "visual_ready_chunk_records": 9,
          "world_running": true,
          "world_snapshot_rejections": 0,
          "world_snapshots": 1
        },
        "edits": 12,
        "frame_count": 2044,
        "frame_sample_count": 255,
        "maximum_collision_queue": 0,
        "maximum_collision_resources": 14,
        "maximum_frame_us": 73449,
        "maximum_memory_bytes": 24901819,
        "maximum_render_queue": 0,
        "maximum_render_resources": 15,
        "migrated_runtime": {
          "active_chunk_records": 0,
          "application_applied_collision": 0,
          "application_applied_render": 0,
          "application_queue_rejections": 0,
          "application_sink_failures": 0,
          "application_stale_collision": 0,
          "application_stale_render": 0,
          "application_submitted_collision": 0,
          "application_submitted_render": 0,
          "application_unrequired_collision": 0,
          "coalesced_viewer_events": 0,
          "collision_latency_frames_maximum": 0,
          "collision_resources": 0,
          "edit_commits": 0,
          "edit_rejections": 0,
          "edit_replacements": 0,
          "fully_ready_chunk_records": 0,
          "mesh_completions": 0,
          "mesh_jobs": 0,
          "pending_chunk_retirements": 0,
          "planned_demands": 0,
          "published_events": 1,
          "queued_collision": 0,
          "queued_render": 0,
          "rejected_events": 0,
          "render_fading_resources": 0,
          "render_latency_frames_maximum": 0,
          "render_resources": 0,
          "sample_jobs": 0,
          "sample_queries": 1,
          "sample_query_rejections": 0,
          "storage_completions": 0,
          "transition_mesh_completions": 0,
          "viewer_removals": 0,
          "viewer_updates": 0,
          "visual_ready_chunk_records": 0,
          "world_running": true,
          "world_snapshot_rejections": 0,
          "world_snapshots": 0
        },
        "movement_steps": 50,
        "observed_collision_chunks": 15,
        "observed_render_chunks": 15,
        "p99_frame_us": 39091,
        "queried_pages": 28,
        "queries": 42,
        "requested_duration_ms": 15000,
        "schema": 1,
        "scope": "clean_install_full_world_godot_soak",
        "shutdown": "clean",
        "source_runtime": {
          "active_chunk_records": 9,
          "application_applied_collision": 443,
          "application_applied_render": 403,
          "application_queue_rejections": 0,
          "application_sink_failures": 0,
          "application_stale_collision": 0,
          "application_stale_render": 0,
          "application_submitted_collision": 443,
          "application_submitted_render": 403,
          "application_unrequired_collision": 0,
          "coalesced_viewer_events": 0,
          "collision_latency_frames_maximum": 1,
          "collision_resources": 5,
          "edit_commits": 12,
          "edit_rejections": 0,
          "edit_replacements": 14,
          "fully_ready_chunk_records": 9,
          "mesh_completions": 403,
          "mesh_jobs": 403,
          "pending_chunk_retirements": 0,
          "planned_demands": 629,
          "published_events": 1722,
          "queued_collision": 0,
          "queued_render": 0,
          "rejected_events": 0,
          "render_fading_resources": 0,
          "render_latency_frames_maximum": 1,
          "render_resources": 5,
          "sample_jobs": 403,
          "sample_queries": 40,
          "sample_query_rejections": 0,
          "storage_completions": 607,
          "transition_mesh_completions": 63,
          "viewer_removals": 10,
          "viewer_updates": 41,
          "visual_ready_chunk_records": 9,
          "world_running": true,
          "world_snapshot_rejections": 0,
          "world_snapshots": 1
        },
        "transition_checks": 100,
        "world_pages": 28
      },
      "runtime_binary_sha256": "c440f32db0ed4234794656a259d88f6b3c83fe18db13dc75c4428c911124867e"
    },
    {
      "configuration": "template_debug",
      "distribution": {
        "bytes": 3963075,
        "file_count": 143,
        "sha256": "70864e37045b707b790b647fea187c74ec717b80d5b04df8f5bf5e2c6de3ce71"
      },
      "engine_sha256": "b2ca888d5115a6cedee564764a2ee494a625f2ec2edbabd010fe33c9a88a6bf8",
      "engine_version": "4.7",
      "runtime": {
        "actual_duration_ms": 15202,
        "compacted_runtime": {
          "active_chunk_records": 9,
          "application_applied_collision": 9,
          "application_applied_render": 9,
          "application_queue_rejections": 0,
          "application_sink_failures": 0,
          "application_stale_collision": 0,
          "application_stale_render": 0,
          "application_submitted_collision": 9,
          "application_submitted_render": 9,
          "application_unrequired_collision": 0,
          "coalesced_viewer_events": 0,
          "collision_latency_frames_maximum": 1,
          "collision_resources": 5,
          "edit_commits": 0,
          "edit_rejections": 0,
          "edit_replacements": 0,
          "fully_ready_chunk_records": 9,
          "mesh_completions": 9,
          "mesh_jobs": 9,
          "pending_chunk_retirements": 0,
          "planned_demands": 9,
          "published_events": 29,
          "queued_collision": 0,
          "queued_render": 0,
          "rejected_events": 0,
          "render_fading_resources": 0,
          "render_latency_frames_maximum": 1,
          "render_resources": 5,
          "sample_jobs": 9,
          "sample_queries": 1,
          "sample_query_rejections": 0,
          "storage_completions": 13,
          "transition_mesh_completions": 1,
          "viewer_removals": 0,
          "viewer_updates": 1,
          "visual_ready_chunk_records": 9,
          "world_running": true,
          "world_snapshot_rejections": 0,
          "world_snapshots": 1
        },
        "edits": 12,
        "frame_count": 1960,
        "frame_sample_count": 245,
        "maximum_collision_queue": 0,
        "maximum_collision_resources": 14,
        "maximum_frame_us": 124113,
        "maximum_memory_bytes": 28132375,
        "maximum_render_queue": 0,
        "maximum_render_resources": 15,
        "migrated_runtime": {
          "active_chunk_records": 0,
          "application_applied_collision": 0,
          "application_applied_render": 0,
          "application_queue_rejections": 0,
          "application_sink_failures": 0,
          "application_stale_collision": 0,
          "application_stale_render": 0,
          "application_submitted_collision": 0,
          "application_submitted_render": 0,
          "application_unrequired_collision": 0,
          "coalesced_viewer_events": 0,
          "collision_latency_frames_maximum": 0,
          "collision_resources": 0,
          "edit_commits": 0,
          "edit_rejections": 0,
          "edit_replacements": 0,
          "fully_ready_chunk_records": 0,
          "mesh_completions": 0,
          "mesh_jobs": 0,
          "pending_chunk_retirements": 0,
          "planned_demands": 0,
          "published_events": 1,
          "queued_collision": 0,
          "queued_render": 0,
          "rejected_events": 0,
          "render_fading_resources": 0,
          "render_latency_frames_maximum": 0,
          "render_resources": 0,
          "sample_jobs": 0,
          "sample_queries": 1,
          "sample_query_rejections": 0,
          "storage_completions": 0,
          "transition_mesh_completions": 0,
          "viewer_removals": 0,
          "viewer_updates": 0,
          "visual_ready_chunk_records": 0,
          "world_running": true,
          "world_snapshot_rejections": 0,
          "world_snapshots": 0
        },
        "movement_steps": 48,
        "observed_collision_chunks": 15,
        "observed_render_chunks": 15,
        "p99_frame_us": 25422,
        "queried_pages": 28,
        "queries": 42,
        "requested_duration_ms": 15000,
        "schema": 1,
        "scope": "clean_install_full_world_godot_soak",
        "shutdown": "clean",
        "source_runtime": {
          "active_chunk_records": 17,
          "application_applied_collision": 423,
          "application_applied_render": 383,
          "application_queue_rejections": 0,
          "application_sink_failures": 0,
          "application_stale_collision": 1,
          "application_stale_render": 1,
          "application_submitted_collision": 424,
          "application_submitted_render": 384,
          "application_unrequired_collision": 0,
          "coalesced_viewer_events": 0,
          "collision_latency_frames_maximum": 1,
          "collision_resources": 9,
          "edit_commits": 12,
          "edit_rejections": 0,
          "edit_replacements": 14,
          "fully_ready_chunk_records": 17,
          "mesh_completions": 384,
          "mesh_jobs": 384,
          "pending_chunk_retirements": 0,
          "planned_demands": 610,
          "published_events": 1638,
          "queued_collision": 0,
          "queued_render": 0,
          "rejected_events": 0,
          "render_fading_resources": 0,
          "render_latency_frames_maximum": 1,
          "render_resources": 9,
          "sample_jobs": 384,
          "sample_queries": 40,
          "sample_query_rejections": 0,
          "storage_completions": 568,
          "transition_mesh_completions": 60,
          "viewer_removals": 10,
          "viewer_updates": 39,
          "visual_ready_chunk_records": 17,
          "world_running": true,
          "world_snapshot_rejections": 0,
          "world_snapshots": 1
        },
        "transition_checks": 96,
        "world_pages": 28
      },
      "runtime_binary_sha256": "c440f32db0ed4234794656a259d88f6b3c83fe18db13dc75c4428c911124867e"
    },
    {
      "configuration": "template_release",
      "distribution": {
        "bytes": 3911363,
        "file_count": 143,
        "sha256": "39510519ba22d73c0865ecee651db83d0b73f08e7171f3dafa1876b68ef9dc16"
      },
      "engine_sha256": "ef90e929ba1a6a4322860285d97f40f4aa349c90329a91b0e8b55b8df0f4cb00",
      "engine_version": "4.6.3",
      "runtime": {
        "actual_duration_ms": 15271,
        "compacted_runtime": {
          "active_chunk_records": 9,
          "application_applied_collision": 9,
          "application_applied_render": 9,
          "application_queue_rejections": 0,
          "application_sink_failures": 0,
          "application_stale_collision": 0,
          "application_stale_render": 0,
          "application_submitted_collision": 9,
          "application_submitted_render": 9,
          "application_unrequired_collision": 0,
          "coalesced_viewer_events": 0,
          "collision_latency_frames_maximum": 1,
          "collision_resources": 5,
          "edit_commits": 0,
          "edit_rejections": 0,
          "edit_replacements": 0,
          "fully_ready_chunk_records": 9,
          "mesh_completions": 9,
          "mesh_jobs": 9,
          "pending_chunk_retirements": 0,
          "planned_demands": 9,
          "published_events": 29,
          "queued_collision": 0,
          "queued_render": 0,
          "rejected_events": 0,
          "render_fading_resources": 0,
          "render_latency_frames_maximum": 1,
          "render_resources": 5,
          "sample_jobs": 9,
          "sample_queries": 1,
          "sample_query_rejections": 0,
          "storage_completions": 13,
          "transition_mesh_completions": 1,
          "viewer_removals": 0,
          "viewer_updates": 1,
          "visual_ready_chunk_records": 9,
          "world_running": true,
          "world_snapshot_rejections": 0,
          "world_snapshots": 1
        },
        "edits": 12,
        "frame_count": 1895,
        "frame_sample_count": 236,
        "maximum_collision_queue": 0,
        "maximum_collision_resources": 14,
        "maximum_frame_us": 107583,
        "maximum_memory_bytes": 24901243,
        "maximum_render_queue": 0,
        "maximum_render_resources": 15,
        "migrated_runtime": {
          "active_chunk_records": 0,
          "application_applied_collision": 0,
          "application_applied_render": 0,
          "application_queue_rejections": 0,
          "application_sink_failures": 0,
          "application_stale_collision": 0,
          "application_stale_render": 0,
          "application_submitted_collision": 0,
          "application_submitted_render": 0,
          "application_unrequired_collision": 0,
          "coalesced_viewer_events": 0,
          "collision_latency_frames_maximum": 0,
          "collision_resources": 0,
          "edit_commits": 0,
          "edit_rejections": 0,
          "edit_replacements": 0,
          "fully_ready_chunk_records": 0,
          "mesh_completions": 0,
          "mesh_jobs": 0,
          "pending_chunk_retirements": 0,
          "planned_demands": 0,
          "published_events": 1,
          "queued_collision": 0,
          "queued_render": 0,
          "rejected_events": 0,
          "render_fading_resources": 0,
          "render_latency_frames_maximum": 0,
          "render_resources": 0,
          "sample_jobs": 0,
          "sample_queries": 1,
          "sample_query_rejections": 0,
          "storage_completions": 0,
          "transition_mesh_completions": 0,
          "viewer_removals": 0,
          "viewer_updates": 0,
          "visual_ready_chunk_records": 0,
          "world_running": true,
          "world_snapshot_rejections": 0,
          "world_snapshots": 0
        },
        "movement_steps": 45,
        "observed_collision_chunks": 15,
        "observed_render_chunks": 15,
        "p99_frame_us": 56907,
        "queried_pages": 28,
        "queries": 42,
        "requested_duration_ms": 15000,
        "schema": 1,
        "scope": "clean_install_full_world_godot_soak",
        "shutdown": "clean",
        "source_runtime": {
          "active_chunk_records": 9,
          "application_applied_collision": 399,
          "application_applied_render": 363,
          "application_queue_rejections": 0,
          "application_sink_failures": 0,
          "application_stale_collision": 2,
          "application_stale_render": 2,
          "application_submitted_collision": 401,
          "application_submitted_render": 365,
          "application_unrequired_collision": 0,
          "coalesced_viewer_events": 0,
          "collision_latency_frames_maximum": 1,
          "collision_resources": 5,
          "edit_commits": 12,
          "edit_rejections": 0,
          "edit_replacements": 14,
          "fully_ready_chunk_records": 9,
          "mesh_completions": 365,
          "mesh_jobs": 365,
          "pending_chunk_retirements": 0,
          "planned_demands": 567,
          "published_events": 1562,
          "queued_collision": 0,
          "queued_render": 0,
          "rejected_events": 0,
          "render_fading_resources": 0,
          "render_latency_frames_maximum": 1,
          "render_resources": 5,
          "sample_jobs": 365,
          "sample_queries": 40,
          "sample_query_rejections": 0,
          "storage_completions": 549,
          "transition_mesh_completions": 57,
          "viewer_removals": 9,
          "viewer_updates": 37,
          "visual_ready_chunk_records": 9,
          "world_running": true,
          "world_snapshot_rejections": 0,
          "world_snapshots": 1
        },
        "transition_checks": 90,
        "world_pages": 28
      },
      "runtime_binary_sha256": "1960c799bb7bec7d949ff5627f4a0834a53fdb836cf69cfcb76d68b758627a5c"
    },
    {
      "configuration": "template_release",
      "distribution": {
        "bytes": 3911363,
        "file_count": 143,
        "sha256": "39510519ba22d73c0865ecee651db83d0b73f08e7171f3dafa1876b68ef9dc16"
      },
      "engine_sha256": "b2ca888d5115a6cedee564764a2ee494a625f2ec2edbabd010fe33c9a88a6bf8",
      "engine_version": "4.7",
      "runtime": {
        "actual_duration_ms": 15144,
        "compacted_runtime": {
          "active_chunk_records": 9,
          "application_applied_collision": 9,
          "application_applied_render": 9,
          "application_queue_rejections": 0,
          "application_sink_failures": 0,
          "application_stale_collision": 0,
          "application_stale_render": 0,
          "application_submitted_collision": 9,
          "application_submitted_render": 9,
          "application_unrequired_collision": 0,
          "coalesced_viewer_events": 0,
          "collision_latency_frames_maximum": 1,
          "collision_resources": 5,
          "edit_commits": 0,
          "edit_rejections": 0,
          "edit_replacements": 0,
          "fully_ready_chunk_records": 9,
          "mesh_completions": 9,
          "mesh_jobs": 9,
          "pending_chunk_retirements": 0,
          "planned_demands": 9,
          "published_events": 29,
          "queued_collision": 0,
          "queued_render": 0,
          "rejected_events": 0,
          "render_fading_resources": 0,
          "render_latency_frames_maximum": 1,
          "render_resources": 5,
          "sample_jobs": 9,
          "sample_queries": 1,
          "sample_query_rejections": 0,
          "storage_completions": 13,
          "transition_mesh_completions": 1,
          "viewer_removals": 0,
          "viewer_updates": 1,
          "visual_ready_chunk_records": 9,
          "world_running": true,
          "world_snapshot_rejections": 0,
          "world_snapshots": 1
        },
        "edits": 12,
        "frame_count": 2091,
        "frame_sample_count": 261,
        "maximum_collision_queue": 0,
        "maximum_collision_resources": 14,
        "maximum_frame_us": 41968,
        "maximum_memory_bytes": 28136839,
        "maximum_render_queue": 0,
        "maximum_render_resources": 15,
        "migrated_runtime": {
          "active_chunk_records": 0,
          "application_applied_collision": 0,
          "application_applied_render": 0,
          "application_queue_rejections": 0,
          "application_sink_failures": 0,
          "application_stale_collision": 0,
          "application_stale_render": 0,
          "application_submitted_collision": 0,
          "application_submitted_render": 0,
          "application_unrequired_collision": 0,
          "coalesced_viewer_events": 0,
          "collision_latency_frames_maximum": 0,
          "collision_resources": 0,
          "edit_commits": 0,
          "edit_rejections": 0,
          "edit_replacements": 0,
          "fully_ready_chunk_records": 0,
          "mesh_completions": 0,
          "mesh_jobs": 0,
          "pending_chunk_retirements": 0,
          "planned_demands": 0,
          "published_events": 1,
          "queued_collision": 0,
          "queued_render": 0,
          "rejected_events": 0,
          "render_fading_resources": 0,
          "render_latency_frames_maximum": 0,
          "render_resources": 0,
          "sample_jobs": 0,
          "sample_queries": 1,
          "sample_query_rejections": 0,
          "storage_completions": 0,
          "transition_mesh_completions": 0,
          "viewer_removals": 0,
          "viewer_updates": 0,
          "visual_ready_chunk_records": 0,
          "world_running": true,
          "world_snapshot_rejections": 0,
          "world_snapshots": 0
        },
        "movement_steps": 57,
        "observed_collision_chunks": 15,
        "observed_render_chunks": 15,
        "p99_frame_us": 14956,
        "queried_pages": 28,
        "queries": 42,
        "requested_duration_ms": 15000,
        "schema": 1,
        "scope": "clean_install_full_world_godot_soak",
        "shutdown": "clean",
        "source_runtime": {
          "active_chunk_records": 25,
          "application_applied_collision": 506,
          "application_applied_render": 458,
          "application_queue_rejections": 0,
          "application_sink_failures": 0,
          "application_stale_collision": 1,
          "application_stale_render": 1,
          "application_submitted_collision": 507,
          "application_submitted_render": 459,
          "application_unrequired_collision": 0,
          "coalesced_viewer_events": 0,
          "collision_latency_frames_maximum": 1,
          "collision_resources": 13,
          "edit_commits": 12,
          "edit_rejections": 0,
          "edit_replacements": 14,
          "fully_ready_chunk_records": 25,
          "mesh_completions": 459,
          "mesh_jobs": 459,
          "pending_chunk_retirements": 0,
          "planned_demands": 734,
          "published_events": 1946,
          "queued_collision": 0,
          "queued_render": 0,
          "rejected_events": 0,
          "render_fading_resources": 0,
          "render_latency_frames_maximum": 1,
          "render_resources": 13,
          "sample_jobs": 459,
          "sample_queries": 40,
          "sample_query_rejections": 0,
          "storage_completions": 691,
          "transition_mesh_completions": 71,
          "viewer_removals": 11,
          "viewer_updates": 47,
          "visual_ready_chunk_records": 25,
          "world_running": true,
          "world_snapshot_rejections": 0,
          "world_snapshots": 1
        },
        "transition_checks": 114,
        "world_pages": 28
      },
      "runtime_binary_sha256": "1960c799bb7bec7d949ff5627f4a0834a53fdb836cf69cfcb76d68b758627a5c"
    }
  ],
  "distribution_manifest_sha256": "0d1666a8b6070e33992dd013298574ee2645e1a77f6af68a8bcc45a3440e3015",
  "host": {
    "architecture": "AMD64",
    "godot_arch": "x86_64",
    "godot_platform": "windows",
    "python": "3.13.7",
    "system": "Windows"
  },
  "requested_duration_ms_per_case": 15000,
  "schema": 1,
  "scope": "pq3_clean_install_full_world_soak"
}
